edc_base/__init__.py
edc_base/address.py
edc_base/apps.py
edc_base/models.py
edc_base/navbars.py
edc_base/system_checks.py
edc_base/urls.py
edc_base/view_mixins.py
edc_base/logging/__init__.py
edc_base/logging/formatters.py
edc_base/logging/handlers.py
edc_base/logging/standard.py
edc_base/migrations/0001_initial.py
edc_base/migrations/0002_auto_20171031_1220.py
edc_base/migrations/0003_auto_20180113_2039.py
edc_base/migrations/0004_auto_20180115_0030.py
edc_base/migrations/0005_userprofile_print_server.py
edc_base/migrations/0006_auto_20180731_2241.py
edc_base/migrations/__init__.py
edc_base/static/.DS_Store
edc_base/static/edc_base/.DS_Store
edc_base/static/edc_base/css/.DS_Store
edc_base/static/edc_base/css/bootstrap-theme.min.css
edc_base/static/edc_base/css/bootstrap.min.css
edc_base/static/edc_base/css/edc_base.css
edc_base/static/edc_base/css/sticky-footer-navbar.css
edc_base/static/edc_base/css/flaticon/Flaticon.eot
edc_base/static/edc_base/css/flaticon/Flaticon.svg
edc_base/static/edc_base/css/flaticon/Flaticon.ttf
edc_base/static/edc_base/css/flaticon/Flaticon.woff
edc_base/static/edc_base/css/flaticon/_flaticon.scss
edc_base/static/edc_base/css/flaticon/flaticon.css
edc_base/static/edc_base/css/flaticon/flaticon.html
edc_base/static/edc_base/css/font-awesome/.DS_Store
edc_base/static/edc_base/css/font-awesome/HELP-US-OUT.txt
edc_base/static/edc_base/css/font-awesome/css/font-awesome.css
edc_base/static/edc_base/css/font-awesome/css/font-awesome.min.css
edc_base/static/edc_base/css/font-awesome/fonts/FontAwesome.otf
edc_base/static/edc_base/css/font-awesome/fonts/fontawesome-webfont.eot
edc_base/static/edc_base/css/font-awesome/fonts/fontawesome-webfont.svg
edc_base/static/edc_base/css/font-awesome/fonts/fontawesome-webfont.ttf
edc_base/static/edc_base/css/font-awesome/fonts/fontawesome-webfont.woff
edc_base/static/edc_base/css/font-awesome/fonts/fontawesome-webfont.woff2
edc_base/static/edc_base/css/font-awesome/less/animated.less
edc_base-0.3.12.dist-info/AUTHORS
edc_base-0.3.12.dist-info/LICENSE
edc_base-0.3.12.dist-info/METADATA
edc_base-0.3.12.dist-info/WHEEL
edc_base-0.3.12.dist-info/top_level.txt
edc_base-0.3.12.dist-info/RECORD
