Metadata-Version: 2.1
Name: edc-base
Version: 0.3.12
Summary: Base mixins and utilities for clinicedc/edc projects.
Home-page: http://github.com/clinicedc/edc-base
Author: Erik van Widenfelt
Author-email: ew2789@gmail.com
License: GPL license, see LICENSE
Keywords: django base models fields forms admin
Platform: UNKNOWN
Classifier: Environment :: Web Environment
Classifier: Framework :: Django
Classifier: Intended Audience :: Developers
Classifier: Intended Audience :: Science/Research
Classifier: License :: OSI Approved :: GNU General Public License v3 (GPLv3)
Classifier: Operating System :: OS Independent
Classifier: Programming Language :: Python :: 3.7
Classifier: Topic :: Internet :: WWW/HTTP
Classifier: Topic :: Internet :: WWW/HTTP :: Dynamic Content
Requires-Python: >=3.7
Requires-Dist: arrow
Requires-Dist: django
Requires-Dist: django-environ
Requires-Dist: django-extensions
Requires-Dist: django-js-reverse
Requires-Dist: django-logentry-admin
Requires-Dist: django-simple-history (>=2.7.0)
Requires-Dist: django-crypto-fields
Requires-Dist: django-revision
Requires-Dist: edc-constants
Requires-Dist: edc-dashboard
Requires-Dist: edc-model-fields
Requires-Dist: edc-navbar
Requires-Dist: edc-protocol
Requires-Dist: mysqlclient
Requires-Dist: python-dateutil
Requires-Dist: python-memcached
Requires-Dist: pytz
Requires-Dist: tqdm
